{
"type": "FeatureCollection",
"name": "garden2",
"crs": { "type": "name", "properties": { "name": "urn:ogc:def:crs:OGC:1.3:CRS84" } },
"features": [
{ "type": "Feature", "properties": { "id": null }, "geometry": { "type": "Point", "coordinates": [ -77.440461036861038, 42.846481935010281 ] } }
]
}
